cwstorm/VERSION
cwstorm/__init__.py
cwstorm/cli.py
cwstorm/deserializer.py
cwstorm/validator.py
cwstorm/version.py
cwstorm/dsl/__init__.py
cwstorm/dsl/cmd.py
cwstorm/dsl/dag_node.py
cwstorm/dsl/email.py
cwstorm/dsl/factory.py
cwstorm/dsl/job.py
cwstorm/dsl/node.py
cwstorm/dsl/node_metaclass.py
cwstorm/dsl/task.py
cwstorm/dsl/upload.py
cwstorm/dsl/work_node.py
cwstorm/examples/__init__.py
cwstorm/examples/all_types_job.py
cwstorm/examples/ass_comp_heavy.py
cwstorm/examples/ass_comp_light.py
cwstorm/examples/ass_comp_normal.py
cwstorm/examples/ass_export.py
cwstorm/examples/frames.py
cwstorm/examples/one_task.py
cwstorm/examples/sim_job.py
cwstorm/examples/simple_qt.py
cwstorm/serializers/__init__.py
cwstorm/serializers/default.py
tests/__init__.py
tests/test_cmd.py
tests/test_dag_node.py
tests/test_deserializer.py
tests/test_job.py
tests/test_node.py
tests/test_serializers.py
tests/test_task.py
cwstorm-2.1.0.dist-info/METADATA
cwstorm-2.1.0.dist-info/WHEEL
cwstorm-2.1.0.dist-info/entry_points.txt
cwstorm-2.1.0.dist-info/top_level.txt
cwstorm-2.1.0.dist-info/RECORD
