Metadata-Version: 2.1
Name: cwstorm
Version: 2.1.0
Summary: DSL for Storm authoring
Home-page: https://github.com/ConductorTechnologies/cwstorm
Author: conductor
Author-email: info@conductortech.com
Classifier: Operating System :: OS Independent
Classifier: Programming Language :: Python
Classifier: Topic :: Multimedia :: Graphics :: 3D Rendering
Requires-Dist: Click
Requires-Dist: pyyaml
Requires-Dist: markdown<4.0.0,>=3.5.2
